shellstats.py
shellstats-0.1.dist-info/RECORD
shellstats-0.1.dist-info/WHEEL
shellstats-0.1.dist-info/top_level.txt
shellstats-0.1.dist-info/entry_points.txt
shellstats-0.1.dist-info/DESCRIPTION.rst
shellstats-0.1.dist-info/METADATA
shellstats-0.1.dist-info/metadata.json
