Metadata-Version: 2.0
Name: shellstats
Version: 0.1
Summary: Show the most used shell commands.
Home-page: https://github.com/rahiel/shellstats
Author: Rahiel Kasim
Author-email: rahielkasim@gmail.com
License: MIT
Platform: UNKNOWN
Classifier: Development Status :: 4 - Beta
Classifier: Intended Audience :: End Users/Desktop
Classifier: Natural Language :: English
Classifier: Topic :: System :: Shells
Classifier: Topic :: Utilities
Classifier: License :: OSI Approved :: MIT License
Classifier: Programming Language :: Python :: 2
Classifier: Programming Language :: Python :: 3
Requires-Dist: click
Provides-Extra: Plotting
Requires-Dist: matplotlib; extra == 'Plotting'
